zern/__init__.py
zern/core/session.py
zern/core/trader.py
zern/core/websocket_connection/ticker.py
zern/utils/OrderedList.py
zern/utils/Types.py
zern/utils/parsing.py
zern-0.0.20.dist-info/licenses/LICENSE
zern-0.0.20.dist-info/METADATA
zern-0.0.20.dist-info/WHEEL
zern-0.0.20.dist-info/top_level.txt
zern-0.0.20.dist-info/RECORD
