Metadata-Version: 2.4
Name: zern
Version: 0.0.20
Summary: An unofficial client library using Zerodha web api for live data and historical data
Author-email: Harsha Avapati <harshaavapati@gmail.com>
Project-URL: Homepage, https://github.com/ExBlacklight/Zern
Project-URL: Issues, https://github.com/ExBlacklight/Zern/issues
Classifier: Programming Language :: Python :: 3
Classifier: License :: OSI Approved :: MIT License
Classifier: Operating System :: OS Independent
Requires-Python: >=3.8
License-File: LICENSE
Requires-Dist: websocket-client
Requires-Dist: pyotp
Requires-Dist: requests
Requires-Dist: certifi
Requires-Dist: numpy
Dynamic: license-file
